path_dict/__init__.py
path_dict/multi_path_dict.py
path_dict/path.py
path_dict/path_dict.py
path_dict/utils.py
path_dict-4.0.0.dist-info/LICENSE
path_dict-4.0.0.dist-info/METADATA
path_dict-4.0.0.dist-info/WHEEL
path_dict-4.0.0.dist-info/RECORD
